CHANGELOG.md
LICENSE
ifpd2/__init__.py
ifpd2/asserts.py
ifpd2/autocomplete/.ifpd2-complete.bash
ifpd2/autocomplete/.ifpd2-complete.fish
ifpd2/autocomplete/.ifpd2-complete.zsh
ifpd2/chromosome.py
ifpd2/const.py
ifpd2/database.py
ifpd2/dataclasses.py
ifpd2/fasta.py
ifpd2/io.py
ifpd2/logging.py
ifpd2/oligo.py
ifpd2/probe.py
ifpd2/probe_set.py
ifpd2/region.py
ifpd2/scripts/__init__.py
ifpd2/scripts/arguments.py
ifpd2/scripts/autocomplete.py
ifpd2/scripts/db/__init__.py
ifpd2/scripts/db/check.py
ifpd2/scripts/db/dump.py
ifpd2/scripts/db/info.py
ifpd2/scripts/db/make.py
ifpd2/scripts/db/run.py
ifpd2/scripts/db/settings.py
ifpd2/scripts/extract_kmers.py
ifpd2/scripts/ifpd2.py
ifpd2/scripts/query.py
ifpd2/scripts/query2.py
ifpd2/tests/__init__.py
ifpd2/tests/test_scripts_db.py
ifpd2/walker.py
ifpd2/walker2.py
ifpd2-1.0.1a1.dist-info/entry_points.txt
ifpd2-1.0.1a1.dist-info/LICENSE
ifpd2-1.0.1a1.dist-info/WHEEL
ifpd2-1.0.1a1.dist-info/METADATA
ifpd2-1.0.1a1.dist-info/RECORD
