Metadata-Version: 2.1
Name: ifpd2
Version: 1.0.1a1
Summary: An iFISH probe design pipeline (II)
Home-page: https://github.com/ggirelli/ifpd2
License: MIT
Keywords: biology,cell,DNA,RNA,FISH,fluorescence,hybridization
Author: Gabriele Girelli
Author-email: gigi.ga90@gmail.com
Requires-Python: >=3.8,<4.0
Classifier: Development Status :: 3 - Alpha
Classifier: Environment :: Console
Classifier: Intended Audience :: Science/Research
Classifier: License :: OSI Approved :: MIT License
Classifier: Operating System :: POSIX :: Linux
Classifier: Operating System :: Unix
Classifier: Programming Language :: Python :: 3
Classifier: Programming Language :: Python :: 3.8
Classifier: Programming Language :: Python :: 3.9
Classifier: Topic :: Scientific/Engineering :: Bio-Informatics
Classifier: Typing :: Typed
Requires-Dist: biopython (>=1.79,<2.0)
Requires-Dist: click (>=8.0.1,<9.0.0)
Requires-Dist: numpy (>=1.20.1,<2.0.0)
Requires-Dist: pandas (>=1.2.2,<2.0.0)
Requires-Dist: rich (>=9.10,<11.0)
Requires-Dist: tqdm (>=4.58.0,<5.0.0)
Project-URL: Repository, https://github.com/ggirelli/ifpd2
